treelyze/__init__.py
treelyze/file_summarizer.py
treelyze/main.py
treelyze/tree_analyzer.py
treelyze-0.1.2.dist-info/LICENSE
treelyze-0.1.2.dist-info/METADATA
treelyze-0.1.2.dist-info/WHEEL
treelyze-0.1.2.dist-info/entry_points.txt
treelyze-0.1.2.dist-info/RECORD
