Metadata-Version: 2.1
Name: treelyze
Version: 0.1.2
Summary: A CLI tool for analyzing directory structures and summarizing files
Home-page: https://github.com/mandgie/treelyze
Keywords: cli,directory,analysis,summarization
Author: Magnus
Author-email: magnus.uno.friberg@gmail.com
Requires-Python: >=3.10,<4.0
Classifier: Programming Language :: Python :: 3
Classifier: Programming Language :: Python :: 3.10
Classifier: Programming Language :: Python :: 3.11
Classifier: Programming Language :: Python :: 3.12
Classifier: Programming Language :: Python :: 3.13
Requires-Dist: pyyaml (>=6.0.2,<7.0.0)
Requires-Dist: requests (>=2.32.3,<3.0.0)
Requires-Dist: typer (>=0.12.5,<0.13.0)
Project-URL: Repository, https://github.com/mandgie/treelyze
